README.txt
setup.py
broken_since/__init__.py
broken_since/broken_since.py
broken_since.egg-info/PKG-INFO
broken_since.egg-info/SOURCES.txt
broken_since.egg-info/dependency_links.txt
broken_since.egg-info/entry_points.txt
broken_since.egg-info/top_level.txt