Metadata-Version: 1.0
Name: broken-since
Version: 0.1.1
Summary:  broken_since nose plugin 
Home-page: UNKNOWN
Author: Francis Pieraut
Author-email: UNKNOWN
License: UNKNOWN
Platform: UNKNOWN
